rtl/pe_stream.v
// Streaming Processing Element 

module pe_stream #(parameter WIDTH=8)(
    input  logic clk,
    input  logic rst,

    input  logic valid_in,
    input  logic [WIDTH-1:0] a_in,
    input  logic [WIDTH-1:0] b_in,

    output logic valid_out,
    output logic [WIDTH-1:0] a_out,
    output logic [WIDTH-1:0] b_out,
    output logic [2*WIDTH-1:0] acc_out
);

// Internal registers-----------------------

    logic [2*WIDTH-1:0] acc;
    logic [1:0] count;

    always_ff @(posedge clk or posedge rst) begin
        if (rst) begin
            acc       <= 0;
            a_out     <= 0;
            b_out     <= 0;
            valid_out <= 0;
            count     <= 0;
        end else begin
            // propagate data
            a_out     <= a_in;
            b_out     <= b_in;
            valid_out <= valid_in;

            // count valid cycles
            if (valid_in)
                count <= count + 1;

            // accumulate only for first 2 cycles (N=2)
            if (valid_in && count < 2) begin
                acc <= acc + (a_in * b_in);
            end
        end
    end

    assign acc_out = acc;

endmodule

rtl/matmul_systolic_stream.v
// 2x2 Systolic Array (Streaming Version)

module matmul_systolic_stream #(parameter WIDTH=8)(
    input logic clk,
    input logic rst,

    input logic valid_in,

    input logic [WIDTH-1:0] A0, A1,   // row 0 stream
    input logic [WIDTH-1:0] B0, B1,   // col 0 stream

    output logic [2*WIDTH-1:0] C00, C01,
    output logic [2*WIDTH-1:0] C10, C11
);

    // internal connections
    logic v00, v01, v10, v11;
    logic [WIDTH-1:0] a00, a01, a10, a11;
    logic [WIDTH-1:0] b00, b01, b10, b11;

    // PE (0,0)
    pe_stream #(WIDTH) pe00 (
        .clk(clk), .rst(rst),
        .valid_in(valid_in),
        .a_in(A0),
        .b_in(B0),
        .valid_out(v00),
        .a_out(a00),
        .b_out(b00),
        .acc_out(C00)
    );

    // PE (0,1)
    pe_stream #(WIDTH) pe01 (
        .clk(clk), .rst(rst),
        .valid_in(v00),
        .a_in(a00),
        .b_in(B1),
        .valid_out(v01),
        .a_out(a01),
        .b_out(b01),
        .acc_out(C01)
    );

    // PE (1,0)
    pe_stream #(WIDTH) pe10 (
        .clk(clk), .rst(rst),
        .valid_in(v00),
        .a_in(A1),
        .b_in(b00),
        .valid_out(v10),
        .a_out(a10),
        .b_out(b10),
        .acc_out(C10)
    );

    // PE (1,1)
    pe_stream #(WIDTH) pe11 (
        .clk(clk), .rst(rst),
        .valid_in(v10),
        .a_in(a10),
        .b_in(b01),
        .valid_out(v11),
        .a_out(a11),
        .b_out(b11),
        .acc_out(C11)
    );

endmodule

rtl/tb_systolic.v
// Testbench for Streaming Systolic Array

module tb_systolic;

    parameter WIDTH = 8;

    logic clk, rst;
    logic valid;

    logic [WIDTH-1:0] A0, A1;
    logic [WIDTH-1:0] B0, B1;

    logic [2*WIDTH-1:0] C00, C01, C10, C11;

    // DUT
    matmul_systolic_stream #(WIDTH) dut (
        .clk(clk), .rst(rst),
        .valid_in(valid),
        .A0(A0), .A1(A1),
        .B0(B0), .B1(B1),
        .C00(C00), .C01(C01),
        .C10(C10), .C11(C11)
    );

    // clock
    always #5 clk = ~clk;

initial begin
    $dumpfile("wave.vcd");
    $dumpvars(0, tb_systolic);

    clk = 0;
    rst = 1;
    valid = 0;

    A0=0; A1=0; B0=0; B1=0;

    // Hold reset
    #20;
    rst = 0;

    // Cycle 1-------------
    valid = 1;
    A0 = 1; A1 = 0;
    B0 = 5; B1 = 0;

    #10;
    
    // Cycle 2-------------
    A0 = 2; A1 = 3;
    B0 = 7; B1 = 6;

    #10;

    // Cycle 3 -------------
    A0 = 0; A1 = 4;
    B0 = 0; B1 = 8;

    #10;

    // Stop input
    valid = 0;

    // Flush pipeline
    #100;

    $display("FINAL OUTPUT:");
    $display("C00=%d C01=%d", C00, C01);
    $display("C10=%d C11=%d", C10, C11);
    #100;
    $finish;
end
endmodule

rtl/matmul_unrolled.v
// Matrix Multiplication (Fully Tool-Safe Version)
// - Uses flat vectors (NO array ports)
// - Fully combinational
// - Guaranteed to work in Icarus Verilog

module matmul_unrolled #(parameter WIDTH=8)(
    input  logic [WIDTH-1:0] A00, A01, A10, A11,
    input  logic [WIDTH-1:0] B00, B01, B10, B11,
    input logic clk,

    output logic [2*WIDTH-1:0] C00, C01, C10, C11
);

    always_comb begin
        C00 = (A00 * B00) + (A01 * B10);
        C01 = (A00 * B01) + (A01 * B11);
        C10 = (A10 * B00) + (A11 * B10);
        C11 = (A10 * B01) + (A11 * B11);
    end

endmodule

rtl/tb_matmul.v
// Testbench

module tb_matmul;

    parameter WIDTH = 8;

    // Inputs
    logic [WIDTH-1:0] A00, A01, A10, A11;
    logic [WIDTH-1:0] B00, B01, B10, B11;

    // Outputs
    logic [2*WIDTH-1:0] C00, C01, C10, C11;

    // DUT
    matmul_unrolled #(WIDTH) dut (
        .A00(A00), .A01(A01),
        .A10(A10), .A11(A11),

        .B00(B00), .B01(B01),
        .B10(B10), .B11(B11),

        .C00(C00), .C01(C01),
        .C10(C10), .C11(C11)
    );

    initial begin
  
    $dumpfile("wave.vcd");   // file name
    $dumpvars(0, tb_matmul); // dump all signals
    
        // Initialize inputs (VERY IMPORTANT)
        A00 = 0; A01 = 0; A10 = 0; A11 = 0;
        B00 = 0; B01 = 0; B10 = 0; B11 = 0;

        #1;

        // Assign values
        // A = [1 2; 3 4]
        // B = [5 6; 7 8]
        A00 = 1; A01 = 2;
        A10 = 3; A11 = 4;

        B00 = 5; B01 = 6;
        B10 = 7; B11 = 8;

        #1;

        $display("Matrix C:");
        $display("C00 = %d", C00);
        $display("C01 = %d", C01);
        $display("C10 = %d", C10);
        $display("C11 = %d", C11);
	#100;
        $finish;
    end

endmodule

sim/wave.vcd
$date
	Fri Mar 27 12:49:36 2026
$end
$version
	Icarus Verilog
$end
$timescale
	1s
$end
$scope module tb_matmul $end
$var wire 16 ! C11 [15:0] $end
$var wire 16 " C10 [15:0] $end
$var wire 16 # C01 [15:0] $end
$var wire 16 $ C00 [15:0] $end
$var parameter 32 % WIDTH $end
$var reg 8 & A00 [7:0] $end
$var reg 8 ' A01 [7:0] $end
$var reg 8 ( A10 [7:0] $end
$var reg 8 ) A11 [7:0] $end
$var reg 8 * B00 [7:0] $end
$var reg 8 + B01 [7:0] $end
$var reg 8 , B10 [7:0] $end
$var reg 8 - B11 [7:0] $end
$scope module dut $end
$var wire 8 . A00 [7:0] $end
$var wire 8 / A01 [7:0] $end
$var wire 8 0 A10 [7:0] $end
$var wire 8 1 A11 [7:0] $end
$var wire 8 2 B00 [7:0] $end
$var wire 8 3 B01 [7:0] $end
$var wire 8 4 B10 [7:0] $end
$var wire 8 5 B11 [7:0] $end
$var wire 1 6 clk $end
$var parameter 32 7 WIDTH $end
$var reg 16 8 C00 [15:0] $end
$var reg 16 9 C01 [15:0] $end
$var reg 16 : C10 [15:0] $end
$var reg 16 ; C11 [15:0] $end
$upscope $end
$upscope $end
$scope module tb_systolic $end
$var wire 16 < C11 [15:0] $end
$var wire 16 = C10 [15:0] $end
$var wire 16 > C01 [15:0] $end
$var wire 16 ? C00 [15:0] $end
$var parameter 32 @ WIDTH $end
$var reg 8 A A0 [7:0] $end
$var reg 8 B A1 [7:0] $end
$var reg 8 C B0 [7:0] $end
$var reg 8 D B1 [7:0] $end
$var reg 1 E clk $end
$var reg 1 F rst $end
$var reg 1 G valid $end
$scope module dut $end
$var wire 8 H A0 [7:0] $end
$var wire 8 I A1 [7:0] $end
$var wire 8 J B0 [7:0] $end
$var wire 8 K B1 [7:0] $end
$var wire 1 E clk $end
$var wire 1 F rst $end
$var wire 1 G valid_in $end
$var wire 1 L v11 $end
$var wire 1 M v10 $end
$var wire 1 N v01 $end
$var wire 1 O v00 $end
$var wire 8 P b11 [7:0] $end
$var wire 8 Q b10 [7:0] $end
$var wire 8 R b01 [7:0] $end
$var wire 8 S b00 [7:0] $end
$var wire 8 T a11 [7:0] $end
$var wire 8 U a10 [7:0] $end
$var wire 8 V a01 [7:0] $end
$var wire 8 W a00 [7:0] $end
$var wire 16 X C11 [15:0] $end
$var wire 16 Y C10 [15:0] $end
$var wire 16 Z C01 [15:0] $end
$var wire 16 [ C00 [15:0] $end
$var parameter 32 \ WIDTH $end
$scope module pe00 $end
$var wire 8 ] a_in [7:0] $end
$var wire 16 ^ acc_out [15:0] $end
$var wire 8 _ b_in [7:0] $end
$var wire 1 E clk $end
$var wire 1 F rst $end
$var wire 1 G valid_in $end
$var parameter 32 ` WIDTH $end
$var reg 8 a a_out [7:0] $end
$var reg 16 b acc [15:0] $end
$var reg 8 c b_out [7:0] $end
$var reg 2 d count [1:0] $end
$var reg 1 O valid_out $end
$upscope $end
$scope module pe01 $end
$var wire 8 e a_in [7:0] $end
$var wire 16 f acc_out [15:0] $end
$var wire 8 g b_in [7:0] $end
$var wire 1 E clk $end
$var wire 1 F rst $end
$var wire 1 O valid_in $end
$var parameter 32 h WIDTH $end
$var reg 8 i a_out [7:0] $end
$var reg 16 j acc [15:0] $end
$var reg 8 k b_out [7:0] $end
$var reg 2 l count [1:0] $end
$var reg 1 N valid_out $end
$upscope $end
$scope module pe10 $end
$var wire 8 m a_in [7:0] $end
$var wire 16 n acc_out [15:0] $end
$var wire 8 o b_in [7:0] $end
$var wire 1 E clk $end
$var wire 1 F rst $end
$var wire 1 O valid_in $end
$var parameter 32 p WIDTH $end
$var reg 8 q a_out [7:0] $end
$var reg 16 r acc [15:0] $end
$var reg 8 s b_out [7:0] $end
$var reg 2 t count [1:0] $end
$var reg 1 M valid_out $end
$upscope $end
$scope module pe11 $end
$var wire 8 u a_in [7:0] $end
$var wire 16 v acc_out [15:0] $end
$var wire 8 w b_in [7:0] $end
$var wire 1 E clk $end
$var wire 1 F rst $end
$var wire 1 M valid_in $end
$var parameter 32 x WIDTH $end
$var reg 8 y a_out [7:0] $end
$var reg 16 z acc [15:0] $end
$var reg 8 { b_out [7:0] $end
$var reg 2 | count [1:0] $end
$var reg 1 L valid_out $end
$upscope $end
$upscope $end
$upscope $end
$enddefinitions $end
$comment Show the parameter values. $end
$dumpall
b1000 x
b1000 p
b1000 h
b1000 `
b1000 \
b1000 @
b1000 7
b1000 %
$end
#0
$dumpvars
b0 |
b0 {
b0 z
b0 y
b0 w
b0 v
b0 u
b0 t
b0 s
b0 r
b0 q
b0 o
b0 n
b0 m
b0 l
b0 k
b0 j
b0 i
b0 g
b0 f
b0 e
b0 d
b0 c
b0 b
b0 a
b0 _
b0 ^
b0 ]
b0 [
b0 Z
b0 Y
b0 X
b0 W
b0 V
b0 U
b0 T
b0 S
b0 R
b0 Q
b0 P
0O
0N
0M
0L
b0 K
b0 J
b0 I
b0 H
0G
1F
0E
b0 D
b0 C
b0 B
b0 A
b0 ?
b0 >
b0 =
b0 <
b0 ;
b0 :
b0 9
b0 8
z6
b0 5
b0 4
b0 3
b0 2
b0 1
b0 0
b0 /
b0 .
b0 -
b0 ,
b0 +
b0 *
b0 )
b0 (
b0 '
b0 &
b0 $
b0 #
b0 "
b0 !
$end
#1
b110010 !
b110010 ;
b101011 "
b101011 :
b10110 #
b10110 9
b10011 $
b10011 8
b1000 -
b1000 5
b111 ,
b111 4
b110 +
b110 3
b101 *
b101 2
b100 )
b100 1
b11 (
b11 0
b10 '
b10 /
b1 &
b1 .
#5
1E
#10
0E
#15
1E
#20
0E
b101 C
b101 J
b101 _
b1 A
b1 H
b1 ]
1G
0F
#25
b101 ?
b101 [
b101 ^
b101 b
b1 d
1O
b101 S
b101 c
b101 o
b1 W
b1 a
b1 e
1E
#30
0E
b110 D
b110 K
b110 g
b111 C
b111 J
b111 _
b11 B
b11 I
b11 m
b10 A
b10 H
b10 ]
#35
b10011 ?
b10011 [
b10011 ^
b10011 b
b10 d
b111 S
b111 c
b111 o
b10 W
b10 a
b10 e
b110 >
b110 Z
b110 f
b110 j
b1 l
1N
b110 R
b110 k
b110 w
b1 V
b1 i
b1111 =
b1111 Y
b1111 n
b1111 r
b1 t
1M
b101 Q
b101 s
b11 U
b11 q
b11 u
1E
#40
0E
b1000 D
b1000 K
b1000 g
b0 C
b0 J
b0 _
b100 B
b100 I
b100 m
b0 A
b0 H
b0 ]
#45
b10010 <
b10010 X
b10010 v
b10010 z
b1 |
1L
b110 P
b110 {
b11 T
b11 y
b101011 =
b101011 Y
b101011 n
b101011 r
b10 t
b111 Q
b111 s
b100 U
b100 q
b100 u
b10110 >
b10110 Z
b10110 f
b10110 j
b10 l
b1000 R
b1000 k
b1000 w
b10 V
b10 i
b11 d
b0 S
b0 c
b0 o
b0 W
b0 a
b0 e
1E
#50
0E
0G
#55
0O
b11 l
b0 V
b0 i
b11 t
b0 Q
b0 s
b110010 <
b110010 X
b110010 v
b110010 z
b10 |
b1000 P
b1000 {
b100 T
b100 y
1E
#60
0E
#65
b11 |
0M
0N
1E
#70
0E
#75
0L
1E
